poetry_codeartifact_auth_plugin/__init__.py
poetry_codeartifact_auth_plugin/plugin.py
poetry_codeartifact_auth_plugin-0.3.1.dist-info/LICENSE
poetry_codeartifact_auth_plugin-0.3.1.dist-info/METADATA
poetry_codeartifact_auth_plugin-0.3.1.dist-info/WHEEL
poetry_codeartifact_auth_plugin-0.3.1.dist-info/entry_points.txt
poetry_codeartifact_auth_plugin-0.3.1.dist-info/RECORD
