Metadata-Version: 2.3
Name: poetry-codeartifact-auth-plugin
Version: 0.3.1
Summary: Poetry plugin to authenticate to codeartifact
Author: Cristian Davis
Author-email: cristian.davis@sandsdev.com
Requires-Python: >=3.10,<4.0
Classifier: Programming Language :: Python :: 3
Classifier: Programming Language :: Python :: 3.10
Classifier: Programming Language :: Python :: 3.11
Classifier: Programming Language :: Python :: 3.12
Classifier: Programming Language :: Python :: 3.13
Requires-Dist: boto3 (>=1.38.2,<2.0.0)
Requires-Dist: poetry (>=2.1.2,<3.0.0)
